LICENSE
MANIFEST.in
README
setup.py
docs/Makefile
docs/source/administrator.rst
docs/source/conf.py
docs/source/exceptions.rst
docs/source/getting_started.rst
docs/source/group.rst
docs/source/index.rst
docs/source/server.rst
docs/source/station.rst
docs/source/tariff.rst
docs/source/utilities.rst
pyavdesk/__init__.py
pyavdesk/pyavdesk.py
pyavdesk/structures.py
pyavdesk/tests.py
pyavdesk.egg-info/PKG-INFO
pyavdesk.egg-info/SOURCES.txt
pyavdesk.egg-info/dependency_links.txt
pyavdesk.egg-info/not-zip-safe
pyavdesk.egg-info/requires.txt
pyavdesk.egg-info/top_level.txt