Metadata-Version: 1.1
Name: pyavdesk
Version: 1.0.1
Summary: pyavdesk is a Python wrapper for dwavdapi C library to manipulate Dr.Web AV-Desk server resources.
Home-page: http://www.drweb.com
Author: Doctor Web, Ltd.
Author-email: support@drweb.com
License: UNKNOWN
Platform: UNKNOWN
Classifier: Development Status :: 4 - Beta
Classifier: Environment :: Other Environment
Classifier: Intended Audience :: Developers
Classifier: License :: Other/Proprietary License
Classifier: Operating System :: OS Independent
Classifier: Programming Language :: Python
Classifier: Topic :: Internet :: WWW/HTTP
